Metadata-Version: 1.0
Name: shell-commands
Version: 0.0.4
Summary: Command DataBase
Home-page: https://gitlab.com/Mussche/shell-commands
Author: Klaas Mussche
Author-email: klaasmussche@gmail.com
License: MIT
Platform: UNKNOWN
